groupify/__init__.py
groupify/cli.py
groupify/make_random_groups.py
groupify-0.1.19.dist-info/licenses/LICENSE
groupify-0.1.19.dist-info/METADATA
groupify-0.1.19.dist-info/WHEEL
groupify-0.1.19.dist-info/entry_points.txt
groupify-0.1.19.dist-info/top_level.txt
groupify-0.1.19.dist-info/RECORD
